[
    {
        "current": [
            {
                "event": 1,
                "points": 49,
                "total_points": 49,
                "rank": 2754001,
                "rank_sort": 2771712,
                "overall_rank": 2754001,
                "bank": 40,
                "value": 1000,
                "event_transfers": 0,
                "event_transfers_cost": 0,
                "points_on_bench": 0
            },
            {
                "event": 2,
                "points": 94,
                "total_points": 143,
                "rank": 240286,
                "rank_sort": 241714,
                "overall_rank": 436708,
                "bank": 10,
                "value": 1000,
                "event_transfers": 1,
                "event_transfers_cost": 0,
                "points_on_bench": 16
            },
            {
                "event": 3,
                "points": 34,
                "total_points": 177,
                "rank": 5454954,
                "rank_sort": 5461326,
                "overall_rank": 922164,
                "bank": 30,
                "value": 1001,
                "event_transfers": 1,
                "event_transfers_cost": 0,
                "points_on_bench": 3
            },
            {
                "event": 4,
                "points": 38,
                "total_points": 215,
                "rank": 5014264,
                "rank_sort": 5020614,
                "overall_rank": 1773006,
                "bank": 14,
                "value": 1005,
                "event_transfers": 1,
                "event_transfers_cost": 0,
                "points_on_bench": 3
            },
            {
                "event": 5,
                "points": 42,
                "total_points": 257,
                "rank": 6069763,
                "rank_sort": 6074093,
                "overall_rank": 2810484,
                "bank": 14,
                "value": 1002,
                "event_transfers": 0,
                "event_transfers_cost": 0,
                "points_on_bench": 6
            },
            {
                "event": 6,
                "points": 52,
                "total_points": 309,
                "rank": 2647901,
                "rank_sort": 2657363,
                "overall_rank": 2643797,
                "bank": 22,
                "value": 1001,
                "event_transfers": 0,
                "event_transfers_cost": 0,
                "points_on_bench": 12
            },
            {
                "event": 7,
                "points": 73,
                "total_points": 382,
                "rank": 426826,
                "rank_sort": 429740,
                "overall_rank": 1748536,
                "bank": 22,
                "value": 1003,
                "event_transfers": 0,
                "event_transfers_cost": 0,
                "points_on_bench": 19
            },
            {
                "event": 8,
                "points": 34,
                "total_points": 416,
                "rank": 6889274,
                "rank_sort": 6889652,
                "overall_rank": 2787897,
                "bank": 28,
                "value": 1006,
                "event_transfers": 2,
                "event_transfers_cost": 0,
                "points_on_bench": 19
            },
            {
                "event": 9,
                "points": 49,
                "total_points": 465,
                "rank": 5067062,
                "rank_sort": 5072456,
                "overall_rank": 3089284,
                "bank": 18,
                "value": 1011,
                "event_transfers": 1,
                "event_transfers_cost": 0,
                "points_on_bench": 4
            },
            {
                "event": 10,
                "points": 58,
                "total_points": 523,
                "rank": 966475,
                "rank_sort": 972822,
                "overall_rank": 2598762,
                "bank": 18,
                "value": 1011,
                "event_transfers": 0,
                "event_transfers_cost": 0,
                "points_on_bench": 27
            },
            {
                "event": 11,
                "points": 55,
                "total_points": 578,
                "rank": 5379212,
                "rank_sort": 5383701,
                "overall_rank": 2931230,
                "bank": 21,
                "value": 1017,
                "event_transfers": 2,
                "event_transfers_cost": 0,
                "points_on_bench": 0
            },
            {
                "event": 12,
                "points": 35,
                "total_points": 613,
                "rank": 6712583,
                "rank_sort": 6713996,
                "overall_rank": 3499187,
                "bank": 13,
                "value": 1019,
                "event_transfers": 1,
                "event_transfers_cost": 0,
                "points_on_bench": 26
            },
            {
                "event": 13,
                "points": 52,
                "total_points": 665,
                "rank": 1219316,
                "rank_sort": 1231320,
                "overall_rank": 3243275,
                "bank": 13,
                "value": 1022,
                "event_transfers": 0,
                "event_transfers_cost": 0,
                "points_on_bench": 16
            },
            {
                "event": 14,
                "points": 57,
                "total_points": 722,
                "rank": 4327680,
                "rank_sort": 4338046,
                "overall_rank": 3360625,
                "bank": 13,
                "value": 1021,
                "event_transfers": 0,
                "event_transfers_cost": 0,
                "points_on_bench": 3
            },
            {
                "event": 15,
                "points": 46,
                "total_points": 768,
                "rank": 2844140,
                "rank_sort": 2854413,
                "overall_rank": 3258767,
                "bank": 2,
                "value": 1021,
                "event_transfers": 1,
                "event_transfers_cost": 0,
                "points_on_bench": 8
            },
            {
                "event": 16,
                "points": 43,
                "total_points": 811,
                "rank": 2657947,
                "rank_sort": 2664343,
                "overall_rank": 3150816,
                "bank": 9,
                "value": 1020,
                "event_transfers": 2,
                "event_transfers_cost": 0,
                "points_on_bench": 3
            },
            {
                "event": 17,
                "points": 45,
                "total_points": 856,
                "rank": 5952506,
                "rank_sort": 5961171,
                "overall_rank": 3465431,
                "bank": 9,
                "value": 1019,
                "event_transfers": 0,
                "event_transfers_cost": 0,
                "points_on_bench": 3
            },
            {
                "event": 18,
                "points": 42,
                "total_points": 898,
                "rank": 1875817,
                "rank_sort": 1878441,
                "overall_rank": 3178294,
                "bank": 78,
                "value": 1021,
                "event_transfers": 2,
                "event_transfers_cost": 0,
                "points_on_bench": 0
            },
            {
                "event": 19,
                "points": 93,
                "total_points": 991,
                "rank": 1421889,
                "rank_sort": 1425257,
                "overall_rank": 2806102,
                "bank": 67,
                "value": 1021,
                "event_transfers": 1,
                "event_transfers_cost": 0,
                "points_on_bench": 16
            },
            {
                "event": 20,
                "points": 57,
                "total_points": 1048,
                "rank": 1095113,
                "rank_sort": 1100552,
                "overall_rank": 2500439,
                "bank": 88,
                "value": 1021,
                "event_transfers": 1,
                "event_transfers_cost": 0,
                "points_on_bench": 8
            },
            {
                "event": 21,
                "points": 59,
                "total_points": 1107,
                "rank": 2151894,
                "rank_sort": 2159131,
                "overall_rank": 2366047,
                "bank": 91,
                "value": 1023,
                "event_transfers": 1,
                "event_transfers_cost": 0,
                "points_on_bench": 7
            },
            {
                "event": 22,
                "points": 52,
                "total_points": 1159,
                "rank": 4720742,
                "rank_sort": 4727575,
                "overall_rank": 2584107,
                "bank": 91,
                "value": 1023,
                "event_transfers": 0,
                "event_transfers_cost": 0,
                "points_on_bench": 1
            },
            {
                "event": 23,
                "points": 65,
                "total_points": 1224,
                "rank": 2875525,
                "rank_sort": 2886292,
                "overall_rank": 2563389,
                "bank": 91,
                "value": 1025,
                "event_transfers": 0,
                "event_transfers_cost": 0,
                "points_on_bench": 5
            },
            {
                "event": 24,
                "points": 52,
                "total_points": 1276,
                "rank": 5016267,
                "rank_sort": 5018180,
                "overall_rank": 2784489,
                "bank": 89,
                "value": 1020,
                "event_transfers": 2,
                "event_transfers_cost": 0,
                "points_on_bench": 12
            },
            {
                "event": 25,
                "points": 49,
                "total_points": 1325,
                "rank": 4831958,
                "rank_sort": 4839683,
                "overall_rank": 2929662,
                "bank": 89,
                "value": 1018,
                "event_transfers": 0,
                "event_transfers_cost": 0,
                "points_on_bench": 2
            },
            {
                "event": 26,
                "points": 87,
                "total_points": 1412,
                "rank": 2016311,
                "rank_sort": 2022103,
                "overall_rank": 2781711,
                "bank": 35,
                "value": 1012,
                "event_transfers": 2,
                "event_transfers_cost": 0,
                "points_on_bench": 4
            },
            {
                "event": 27,
                "points": 86,
                "total_points": 1498,
                "rank": 811243,
                "rank_sort": 814558,
                "overall_rank": 2499208,
                "bank": 35,
                "value": 1013,
                "event_transfers": 0,
                "event_transfers_cost": 0,
                "points_on_bench": 5
            },
            {
                "event": 28,
                "points": 46,
                "total_points": 1544,
                "rank": 3261245,
                "rank_sort": 3278157,
                "overall_rank": 2492054,
                "bank": 35,
                "value": 1016,
                "event_transfers": 0,
                "event_transfers_cost": 0,
                "points_on_bench": 2
            },
            {
                "event": 29,
                "points": 15,
                "total_points": 1559,
                "rank": 5343064,
                "rank_sort": 5357913,
                "overall_rank": 2659758,
                "bank": 35,
                "value": 1013,
                "event_transfers": 0,
                "event_transfers_cost": 0,
                "points_on_bench": 1
            },
            {
                "event": 30,
                "points": 21,
                "total_points": 1580,
                "rank": 8020656,
                "rank_sort": 8022242,
                "overall_rank": 2961374,
                "bank": 35,
                "value": 1011,
                "event_transfers": 0,
                "event_transfers_cost": 0,
                "points_on_bench": 2
            },
            {
                "event": 31,
                "points": 34,
                "total_points": 1614,
                "rank": 5592263,
                "rank_sort": 5607015,
                "overall_rank": 3047413,
                "bank": 35,
                "value": 1009,
                "event_transfers": 0,
                "event_transfers_cost": 0,
                "points_on_bench": 7
            },
            {
                "event": 32,
                "points": 28,
                "total_points": 1642,
                "rank": 7301016,
                "rank_sort": 7308649,
                "overall_rank": 3246406,
                "bank": 35,
                "value": 1007,
                "event_transfers": 0,
                "event_transfers_cost": 0,
                "points_on_bench": 0
            },
            {
                "event": 33,
                "points": 27,
                "total_points": 1669,
                "rank": 6055869,
                "rank_sort": 6070483,
                "overall_rank": 3330945,
                "bank": 35,
                "value": 1004,
                "event_transfers": 0,
                "event_transfers_cost": 0,
                "points_on_bench": 0
            },
            {
                "event": 34,
                "points": 52,
                "total_points": 1721,
                "rank": 1272620,
                "rank_sort": 1282957,
                "overall_rank": 3201821,
                "bank": 35,
                "value": 1002,
                "event_transfers": 0,
                "event_transfers_cost": 0,
                "points_on_bench": 0
            },
            {
                "event": 35,
                "points": 86,
                "total_points": 1807,
                "rank": 3560847,
                "rank_sort": 3570013,
                "overall_rank": 3174601,
                "bank": 35,
                "value": 1002,
                "event_transfers": 0,
                "event_transfers_cost": 0,
                "points_on_bench": 25
            },
            {
                "event": 36,
                "points": 35,
                "total_points": 1842,
                "rank": 4687794,
                "rank_sort": 4701726,
                "overall_rank": 3219080,
                "bank": 35,
                "value": 1003,
                "event_transfers": 0,
                "event_transfers_cost": 0,
                "points_on_bench": 0
            },
            {
                "event": 37,
                "points": 36,
                "total_points": 1878,
                "rank": 5965313,
                "rank_sort": 5979393,
                "overall_rank": 3322790,
                "bank": 35,
                "value": 1005,
                "event_transfers": 0,
                "event_transfers_cost": 0,
                "points_on_bench": 3
            },
            {
                "event": 38,
                "points": 48,
                "total_points": 1926,
                "rank": 4346483,
                "rank_sort": 4362814,
                "overall_rank": 3334884,
                "bank": 35,
                "value": 1004,
                "event_transfers": 0,
                "event_transfers_cost": 0,
                "points_on_bench": 3
            }
        ],
        "past": [
            {
                "season_name": "2015/16",
                "total_points": 1755,
                "rank": 1995767
            },
            {
                "season_name": "2016/17",
                "total_points": 1544,
                "rank": 3339617
            },
            {
                "season_name": "2017/18",
                "total_points": 1557,
                "rank": 4483896
            },
            {
                "season_name": "2018/19",
                "total_points": 1984,
                "rank": 2074620
            },
            {
                "season_name": "2019/20",
                "total_points": 2048,
                "rank": 1383817
            },
            {
                "season_name": "2020/21",
                "total_points": 1926,
                "rank": 3334884
            }
        ],
        "chips": [
            {
                "name": "freehit",
                "time": "2020-10-16T22:39:44.881234Z",
                "event": 5
            },
            {
                "name": "wildcard",
                "time": "2020-10-18T21:06:54.475605Z",
                "event": 6
            }
        ]
    },
    {
        "id": 1029246,
        "joined_time": "2020-08-20T10:53:39.696492Z",
        "started_event": 1,
        "favourite_team": null,
        "player_first_name": "Zeen",
        "player_last_name": "Lam",
        "player_region_id": 241,
        "player_region_name": "England",
        "player_region_iso_code_short": "EN",
        "player_region_iso_code_long": "ENG",
        "summary_overall_points": 1926,
        "summary_overall_rank": 3334884,
        "summary_event_points": 48,
        "summary_event_rank": 4346483,
        "current_event": 38,
        "leagues": {
            "classic": [
                {
                    "id": 261,
                    "name": "England",
                    "short_name": "region-241",
                    "created": "2020-08-15T09:00:51.512249Z",
                    "closed": false,
                    "rank": null,
                    "max_entries": null,
                    "league_type": "s",
                    "scoring": "c",
                    "admin_entry": null,
                    "start_event": 1,
                    "entry_can_leave": false,
                    "entry_can_admin": false,
                    "entry_can_invite": false,
                    "has_cup": false,
                    "cup_league": null,
                    "cup_qualified": null,
                    "entry_rank": 1004046,
                    "entry_last_rank": 999611
                },
                {
                    "id": 276,
                    "name": "Gameweek 1",
                    "short_name": "event-1",
                    "created": "2020-08-15T09:00:52.298412Z",
                    "closed": false,
                    "rank": null,
                    "max_entries": null,
                    "league_type": "s",
                    "scoring": "c",
                    "admin_entry": null,
                    "start_event": 1,
                    "entry_can_leave": false,
                    "entry_can_admin": false,
                    "entry_can_invite": false,
                    "has_cup": false,
                    "cup_league": null,
                    "cup_qualified": null,
                    "entry_rank": 3106644,
                    "entry_last_rank": 3098248
                },
                {
                    "id": 314,
                    "name": "Overall",
                    "short_name": "overall",
                    "created": "2020-08-15T09:00:54.021038Z",
                    "closed": false,
                    "rank": null,
                    "max_entries": null,
                    "league_type": "s",
                    "scoring": "c",
                    "admin_entry": null,
                    "start_event": 1,
                    "entry_can_leave": false,
                    "entry_can_admin": false,
                    "entry_can_invite": false,
                    "has_cup": true,
                    "cup_league": 315,
                    "cup_qualified": true,
                    "entry_rank": 3334884,
                    "entry_last_rank": 3322790
                },
                {
                    "id": 357383,
                    "name": "London Mandem",
                    "short_name": null,
                    "created": "2020-08-25T22:41:55.449080Z",
                    "closed": false,
                    "rank": null,
                    "max_entries": null,
                    "league_type": "x",
                    "scoring": "c",
                    "admin_entry": 979495,
                    "start_event": 1,
                    "entry_can_leave": true,
                    "entry_can_admin": false,
                    "entry_can_invite": false,
                    "has_cup": false,
                    "cup_league": null,
                    "cup_qualified": null,
                    "entry_rank": 8,
                    "entry_last_rank": 8
                }
            ],
            "h2h": [],
            "cup": {
                "matches": [
                    {
                        "id": 44393254,
                        "entry_1_entry": 1029246,
                        "entry_1_name": "We Are Coders",
                        "entry_1_player_name": "Zeen Lam",
                        "entry_1_points": 45,
                        "entry_1_win": 0,
                        "entry_1_draw": 0,
                        "entry_1_loss": 0,
                        "entry_1_total": 0,
                        "entry_2_entry": 6461324,
                        "entry_2_name": "Kun One",
                        "entry_2_player_name": "Kun Kun",
                        "entry_2_points": 55,
                        "entry_2_win": 0,
                        "entry_2_draw": 0,
                        "entry_2_loss": 0,
                        "entry_2_total": 0,
                        "is_knockout": true,
                        "winner": 6461324,
                        "seed_value": null,
                        "event": 17,
                        "tiebreak": null
                    }
                ],
                "status": {
                    "qualification_event": 16,
                    "qualification_numbers": 4194304,
                    "qualification_rank": 2657947,
                    "qualification_state": "QUALIFIED"
                },
                "cup_league": 315
            }
        },
        "name": "We Are Coders",
        "kit": null,
        "last_deadline_bank": 35,
        "last_deadline_value": 1004,
        "last_deadline_total_transfers": 21
    }
]