[
    {
        "current": [
            {
                "event": 1,
                "points": 67,
                "total_points": 67,
                "rank": 1055000,
                "rank_sort": 1057573,
                "overall_rank": 1055000,
                "bank": 15,
                "value": 1000,
                "event_transfers": 0,
                "event_transfers_cost": 0,
                "points_on_bench": 4
            },
            {
                "event": 2,
                "points": 43,
                "total_points": 110,
                "rank": 5306798,
                "rank_sort": 5307602,
                "overall_rank": 2647942,
                "bank": 30,
                "value": 1000,
                "event_transfers": 1,
                "event_transfers_cost": 0,
                "points_on_bench": 9
            },
            {
                "event": 3,
                "points": 62,
                "total_points": 168,
                "rank": 504556,
                "rank_sort": 504841,
                "overall_rank": 1494062,
                "bank": 30,
                "value": 1002,
                "event_transfers": 2,
                "event_transfers_cost": 4,
                "points_on_bench": 2
            },
            {
                "event": 4,
                "points": 74,
                "total_points": 238,
                "rank": 571731,
                "rank_sort": 572056,
                "overall_rank": 735867,
                "bank": 9,
                "value": 1004,
                "event_transfers": 2,
                "event_transfers_cost": 4,
                "points_on_bench": 4
            },
            {
                "event": 5,
                "points": 60,
                "total_points": 298,
                "rank": 3642604,
                "rank_sort": 3643664,
                "overall_rank": 926253,
                "bank": 34,
                "value": 1006,
                "event_transfers": 1,
                "event_transfers_cost": 0,
                "points_on_bench": 4
            },
            {
                "event": 6,
                "points": 42,
                "total_points": 336,
                "rank": 4993908,
                "rank_sort": 4994931,
                "overall_rank": 1422362,
                "bank": 0,
                "value": 1011,
                "event_transfers": 2,
                "event_transfers_cost": 4,
                "points_on_bench": 13
            },
            {
                "event": 7,
                "points": 73,
                "total_points": 409,
                "rank": 458711,
                "rank_sort": 459162,
                "overall_rank": 785219,
                "bank": 4,
                "value": 1010,
                "event_transfers": 1,
                "event_transfers_cost": 0,
                "points_on_bench": 2
            },
            {
                "event": 8,
                "points": 86,
                "total_points": 495,
                "rank": 61797,
                "rank_sort": 61903,
                "overall_rank": 301592,
                "bank": 4,
                "value": 1015,
                "event_transfers": 0,
                "event_transfers_cost": 0,
                "points_on_bench": 16
            },
            {
                "event": 9,
                "points": 69,
                "total_points": 564,
                "rank": 1457392,
                "rank_sort": 1458786,
                "overall_rank": 220968,
                "bank": 25,
                "value": 1017,
                "event_transfers": 2,
                "event_transfers_cost": 0,
                "points_on_bench": 6
            },
            {
                "event": 10,
                "points": 57,
                "total_points": 621,
                "rank": 1164738,
                "rank_sort": 1166381,
                "overall_rank": 167438,
                "bank": 2,
                "value": 1015,
                "event_transfers": 1,
                "event_transfers_cost": 0,
                "points_on_bench": 2
            },
            {
                "event": 11,
                "points": 85,
                "total_points": 706,
                "rank": 404693,
                "rank_sort": 405281,
                "overall_rank": 86030,
                "bank": 7,
                "value": 1018,
                "event_transfers": 1,
                "event_transfers_cost": 0,
                "points_on_bench": 1
            },
            {
                "event": 12,
                "points": 70,
                "total_points": 776,
                "rank": 552928,
                "rank_sort": 553603,
                "overall_rank": 54817,
                "bank": 7,
                "value": 1019,
                "event_transfers": 0,
                "event_transfers_cost": 0,
                "points_on_bench": 2
            },
            {
                "event": 13,
                "points": 45,
                "total_points": 821,
                "rank": 3210156,
                "rank_sort": 3212503,
                "overall_rank": 60502,
                "bank": 0,
                "value": 1023,
                "event_transfers": 1,
                "event_transfers_cost": 0,
                "points_on_bench": 1
            },
            {
                "event": 14,
                "points": 76,
                "total_points": 897,
                "rank": 1500418,
                "rank_sort": 1501031,
                "overall_rank": 59413,
                "bank": 0,
                "value": 1022,
                "event_transfers": 2,
                "event_transfers_cost": 0,
                "points_on_bench": 0
            },
            {
                "event": 15,
                "points": 48,
                "total_points": 941,
                "rank": 2454847,
                "rank_sort": 2456456,
                "overall_rank": 79567,
                "bank": 0,
                "value": 1024,
                "event_transfers": 2,
                "event_transfers_cost": 4,
                "points_on_bench": 0
            },
            {
                "event": 16,
                "points": 65,
                "total_points": 1006,
                "rank": 55777,
                "rank_sort": 56061,
                "overall_rank": 35722,
                "bank": 3,
                "value": 1020,
                "event_transfers": 0,
                "event_transfers_cost": 0,
                "points_on_bench": 0
            },
            {
                "event": 17,
                "points": 74,
                "total_points": 1080,
                "rank": 855746,
                "rank_sort": 857047,
                "overall_rank": 24372,
                "bank": 4,
                "value": 1026,
                "event_transfers": 1,
                "event_transfers_cost": 0,
                "points_on_bench": 3
            },
            {
                "event": 18,
                "points": 48,
                "total_points": 1128,
                "rank": 1047512,
                "rank_sort": 1051615,
                "overall_rank": 24483,
                "bank": 4,
                "value": 1027,
                "event_transfers": 0,
                "event_transfers_cost": 0,
                "points_on_bench": 2
            },
            {
                "event": 19,
                "points": 125,
                "total_points": 1241,
                "rank": 132828,
                "rank_sort": 132918,
                "overall_rank": 13528,
                "bank": 3,
                "value": 1026,
                "event_transfers": 4,
                "event_transfers_cost": 12,
                "points_on_bench": 0
            },
            {
                "event": 20,
                "points": 95,
                "total_points": 1336,
                "rank": 3616,
                "rank_sort": 3624,
                "overall_rank": 1371,
                "bank": 66,
                "value": 1028,
                "event_transfers": 1,
                "event_transfers_cost": 0,
                "points_on_bench": 2
            },
            {
                "event": 21,
                "points": 41,
                "total_points": 1373,
                "rank": 5371595,
                "rank_sort": 5372222,
                "overall_rank": 5737,
                "bank": 11,
                "value": 1032,
                "event_transfers": 2,
                "event_transfers_cost": 4,
                "points_on_bench": 4
            },
            {
                "event": 22,
                "points": 89,
                "total_points": 1462,
                "rank": 400482,
                "rank_sort": 401068,
                "overall_rank": 3480,
                "bank": 11,
                "value": 1034,
                "event_transfers": 0,
                "event_transfers_cost": 0,
                "points_on_bench": 6
            },
            {
                "event": 23,
                "points": 72,
                "total_points": 1534,
                "rank": 1673194,
                "rank_sort": 1674102,
                "overall_rank": 3219,
                "bank": 22,
                "value": 1041,
                "event_transfers": 2,
                "event_transfers_cost": 0,
                "points_on_bench": 22
            },
            {
                "event": 24,
                "points": 112,
                "total_points": 1646,
                "rank": 78269,
                "rank_sort": 78398,
                "overall_rank": 1097,
                "bank": 22,
                "value": 1043,
                "event_transfers": 1,
                "event_transfers_cost": 0,
                "points_on_bench": 3
            },
            {
                "event": 25,
                "points": 86,
                "total_points": 1732,
                "rank": 313495,
                "rank_sort": 314311,
                "overall_rank": 744,
                "bank": 20,
                "value": 1044,
                "event_transfers": 1,
                "event_transfers_cost": 0,
                "points_on_bench": 20
            },
            {
                "event": 26,
                "points": 78,
                "total_points": 1802,
                "rank": 3622285,
                "rank_sort": 3622783,
                "overall_rank": 1887,
                "bank": 0,
                "value": 1040,
                "event_transfers": 3,
                "event_transfers_cost": 8,
                "points_on_bench": 16
            },
            {
                "event": 27,
                "points": 72,
                "total_points": 1874,
                "rank": 2187975,
                "rank_sort": 2188783,
                "overall_rank": 2037,
                "bank": 0,
                "value": 1041,
                "event_transfers": 0,
                "event_transfers_cost": 0,
                "points_on_bench": 17
            },
            {
                "event": 28,
                "points": 48,
                "total_points": 1922,
                "rank": 2883460,
                "rank_sort": 2885431,
                "overall_rank": 2151,
                "bank": 1,
                "value": 1041,
                "event_transfers": 1,
                "event_transfers_cost": 0,
                "points_on_bench": 5
            },
            {
                "event": 29,
                "points": 64,
                "total_points": 1982,
                "rank": 277845,
                "rank_sort": 278060,
                "overall_rank": 1447,
                "bank": 47,
                "value": 1037,
                "event_transfers": 3,
                "event_transfers_cost": 4,
                "points_on_bench": 0
            },
            {
                "event": 30,
                "points": 67,
                "total_points": 2049,
                "rank": 468820,
                "rank_sort": 469984,
                "overall_rank": 1036,
                "bank": 50,
                "value": 1039,
                "event_transfers": 1,
                "event_transfers_cost": 0,
                "points_on_bench": 6
            },
            {
                "event": 31,
                "points": 52,
                "total_points": 2101,
                "rank": 1728793,
                "rank_sort": 1729632,
                "overall_rank": 1298,
                "bank": 26,
                "value": 1037,
                "event_transfers": 1,
                "event_transfers_cost": 0,
                "points_on_bench": 21
            },
            {
                "event": 32,
                "points": 75,
                "total_points": 2176,
                "rank": 311111,
                "rank_sort": 311696,
                "overall_rank": 1079,
                "bank": 41,
                "value": 1037,
                "event_transfers": 1,
                "event_transfers_cost": 0,
                "points_on_bench": 9
            },
            {
                "event": 33,
                "points": 57,
                "total_points": 2229,
                "rank": 586893,
                "rank_sort": 588231,
                "overall_rank": 1151,
                "bank": 22,
                "value": 1037,
                "event_transfers": 2,
                "event_transfers_cost": 4,
                "points_on_bench": 2
            },
            {
                "event": 34,
                "points": 38,
                "total_points": 2267,
                "rank": 4349341,
                "rank_sort": 4350682,
                "overall_rank": 1253,
                "bank": 4,
                "value": 1039,
                "event_transfers": 1,
                "event_transfers_cost": 0,
                "points_on_bench": 7
            },
            {
                "event": 35,
                "points": 134,
                "total_points": 2393,
                "rank": 158220,
                "rank_sort": 158450,
                "overall_rank": 1001,
                "bank": 0,
                "value": 1034,
                "event_transfers": 3,
                "event_transfers_cost": 8,
                "points_on_bench": 17
            },
            {
                "event": 36,
                "points": 59,
                "total_points": 2452,
                "rank": 545790,
                "rank_sort": 546472,
                "overall_rank": 705,
                "bank": 30,
                "value": 1029,
                "event_transfers": 0,
                "event_transfers_cost": 0,
                "points_on_bench": 13
            },
            {
                "event": 37,
                "points": 55,
                "total_points": 2507,
                "rank": 1515821,
                "rank_sort": 1517356,
                "overall_rank": 600,
                "bank": 12,
                "value": 1035,
                "event_transfers": 1,
                "event_transfers_cost": 0,
                "points_on_bench": 8
            },
            {
                "event": 38,
                "points": 73,
                "total_points": 2580,
                "rank": 280134,
                "rank_sort": 280448,
                "overall_rank": 358,
                "bank": 7,
                "value": 1039,
                "event_transfers": 1,
                "event_transfers_cost": 0,
                "points_on_bench": 3
            }
        ],
        "past": [
            {
                "season_name": "2007/08",
                "total_points": 1904,
                "rank": 344617
            },
            {
                "season_name": "2008/09",
                "total_points": 1854,
                "rank": 164190
            },
            {
                "season_name": "2009/10",
                "total_points": 2220,
                "rank": 59729
            },
            {
                "season_name": "2010/11",
                "total_points": 2163,
                "rank": 2508
            },
            {
                "season_name": "2011/12",
                "total_points": 2138,
                "rank": 21114
            },
            {
                "season_name": "2012/13",
                "total_points": 2159,
                "rank": 26658
            },
            {
                "season_name": "2013/14",
                "total_points": 2351,
                "rank": 31291
            },
            {
                "season_name": "2014/15",
                "total_points": 2191,
                "rank": 11120
            },
            {
                "season_name": "2015/16",
                "total_points": 2124,
                "rank": 158513
            },
            {
                "season_name": "2016/17",
                "total_points": 2063,
                "rank": 350481
            },
            {
                "season_name": "2017/18",
                "total_points": 2277,
                "rank": 26275
            },
            {
                "season_name": "2018/19",
                "total_points": 2414,
                "rank": 4611
            },
            {
                "season_name": "2019/20",
                "total_points": 2323,
                "rank": 28184
            },
            {
                "season_name": "2020/21",
                "total_points": 2580,
                "rank": 358
            }
        ],
        "chips": [
            {
                "name": "wildcard",
                "time": "2020-12-27T01:11:42.739707Z",
                "event": 16
            },
            {
                "name": "freehit",
                "time": "2021-01-01T18:51:10.551135Z",
                "event": 18
            },
            {
                "name": "bboost",
                "time": "2021-01-16T01:23:25.195338Z",
                "event": 19
            },
            {
                "name": "3xc",
                "time": "2021-02-25T23:53:40.970026Z",
                "event": 26
            },
            {
                "name": "wildcard",
                "time": "2021-05-07T23:07:56.190885Z",
                "event": 36
            }
        ]
    },
    {
        "id": 140082,
        "joined_time": "2020-08-15T13:10:23.035506Z",
        "started_event": 1,
        "favourite_team": 12,
        "player_first_name": "Adam",
        "player_last_name": "Bergin",
        "player_region_id": 241,
        "player_region_name": "England",
        "player_region_iso_code_short": "EN",
        "player_region_iso_code_long": "ENG",
        "summary_overall_points": 2580,
        "summary_overall_rank": 358,
        "summary_event_points": 73,
        "summary_event_rank": 280134,
        "current_event": 38,
        "leagues": {
            "classic": [
                {
                    "id": 314,
                    "name": "Overall",
                    "short_name": "overall",
                    "created": "2020-08-15T09:00:54.021038Z",
                    "closed": false,
                    "rank": null,
                    "max_entries": null,
                    "league_type": "s",
                    "scoring": "c",
                    "admin_entry": null,
                    "start_event": 1,
                    "entry_can_leave": false,
                    "entry_can_admin": false,
                    "entry_can_invite": false,
                    "has_cup": true,
                    "cup_league": 315,
                    "cup_qualified": true,
                    "entry_rank": 358,
                    "entry_last_rank": 600
                },
                {
                    "id": 12,
                    "name": "Man City",
                    "short_name": "team-12",
                    "created": "2020-08-15T09:00:47.030026Z",
                    "closed": false,
                    "rank": null,
                    "max_entries": null,
                    "league_type": "s",
                    "scoring": "c",
                    "admin_entry": null,
                    "start_event": 1,
                    "entry_can_leave": false,
                    "entry_can_admin": false,
                    "entry_can_invite": false,
                    "has_cup": false,
                    "cup_league": null,
                    "cup_qualified": null,
                    "entry_rank": 14,
                    "entry_last_rank": 24
                },
                {
                    "id": 261,
                    "name": "England",
                    "short_name": "region-241",
                    "created": "2020-08-15T09:00:51.512249Z",
                    "closed": false,
                    "rank": null,
                    "max_entries": null,
                    "league_type": "s",
                    "scoring": "c",
                    "admin_entry": null,
                    "start_event": 1,
                    "entry_can_leave": false,
                    "entry_can_admin": false,
                    "entry_can_invite": false,
                    "has_cup": false,
                    "cup_league": null,
                    "cup_qualified": null,
                    "entry_rank": 94,
                    "entry_last_rank": 167
                },
                {
                    "id": 276,
                    "name": "Gameweek 1",
                    "short_name": "event-1",
                    "created": "2020-08-15T09:00:52.298412Z",
                    "closed": false,
                    "rank": null,
                    "max_entries": null,
                    "league_type": "s",
                    "scoring": "c",
                    "admin_entry": null,
                    "start_event": 1,
                    "entry_can_leave": false,
                    "entry_can_admin": false,
                    "entry_can_invite": false,
                    "has_cup": false,
                    "cup_league": null,
                    "cup_qualified": null,
                    "entry_rank": 358,
                    "entry_last_rank": 600
                },
                {
                    "id": 31071,
                    "name": "Pique Muscle",
                    "short_name": null,
                    "created": "2020-08-15T13:37:18.411294Z",
                    "closed": false,
                    "rank": null,
                    "max_entries": null,
                    "league_type": "x",
                    "scoring": "c",
                    "admin_entry": 140082,
                    "start_event": 1,
                    "entry_can_leave": false,
                    "entry_can_admin": true,
                    "entry_can_invite": true,
                    "has_cup": false,
                    "cup_league": null,
                    "cup_qualified": null,
                    "entry_rank": 1,
                    "entry_last_rank": 1
                },
                {
                    "id": 111864,
                    "name": "Fantasy Football Scout",
                    "short_name": null,
                    "created": "2020-08-16T20:01:34.129079Z",
                    "closed": false,
                    "rank": null,
                    "max_entries": null,
                    "league_type": "x",
                    "scoring": "c",
                    "admin_entry": 44593,
                    "start_event": 1,
                    "entry_can_leave": true,
                    "entry_can_admin": false,
                    "entry_can_invite": false,
                    "has_cup": false,
                    "cup_league": null,
                    "cup_qualified": null,
                    "entry_rank": 48,
                    "entry_last_rank": 80
                },
                {
                    "id": 197981,
                    "name": "FPL BlackBox",
                    "short_name": null,
                    "created": "2020-08-19T16:25:50.492480Z",
                    "closed": false,
                    "rank": null,
                    "max_entries": null,
                    "league_type": "x",
                    "scoring": "c",
                    "admin_entry": 2943,
                    "start_event": 1,
                    "entry_can_leave": true,
                    "entry_can_admin": false,
                    "entry_can_invite": false,
                    "has_cup": false,
                    "cup_league": null,
                    "cup_qualified": null,
                    "entry_rank": 33,
                    "entry_last_rank": 43
                },
                {
                    "id": 228960,
                    "name": "£ 10 league",
                    "short_name": null,
                    "created": "2020-08-20T14:30:43.245145Z",
                    "closed": false,
                    "rank": null,
                    "max_entries": null,
                    "league_type": "x",
                    "scoring": "c",
                    "admin_entry": 203404,
                    "start_event": 1,
                    "entry_can_leave": true,
                    "entry_can_admin": false,
                    "entry_can_invite": false,
                    "has_cup": false,
                    "cup_league": null,
                    "cup_qualified": null,
                    "entry_rank": 1,
                    "entry_last_rank": 1
                },
                {
                    "id": 355187,
                    "name": "Ultimate AQA League",
                    "short_name": null,
                    "created": "2020-08-25T20:09:52.547670Z",
                    "closed": false,
                    "rank": null,
                    "max_entries": null,
                    "league_type": "x",
                    "scoring": "c",
                    "admin_entry": 791890,
                    "start_event": 1,
                    "entry_can_leave": true,
                    "entry_can_admin": false,
                    "entry_can_invite": true,
                    "has_cup": false,
                    "cup_league": null,
                    "cup_qualified": null,
                    "entry_rank": 1,
                    "entry_last_rank": 1
                },
                {
                    "id": 438191,
                    "name": "All Quarantined Associates",
                    "short_name": null,
                    "created": "2020-08-29T16:43:01.368392Z",
                    "closed": false,
                    "rank": null,
                    "max_entries": null,
                    "league_type": "x",
                    "scoring": "c",
                    "admin_entry": 1997788,
                    "start_event": 1,
                    "entry_can_leave": true,
                    "entry_can_admin": false,
                    "entry_can_invite": false,
                    "has_cup": false,
                    "cup_league": null,
                    "cup_qualified": null,
                    "entry_rank": 1,
                    "entry_last_rank": 1
                },
                {
                    "id": 487611,
                    "name": "League of gentleman",
                    "short_name": null,
                    "created": "2020-08-31T22:31:41.916261Z",
                    "closed": false,
                    "rank": null,
                    "max_entries": null,
                    "league_type": "x",
                    "scoring": "c",
                    "admin_entry": 2227825,
                    "start_event": 1,
                    "entry_can_leave": true,
                    "entry_can_admin": false,
                    "entry_can_invite": false,
                    "has_cup": false,
                    "cup_league": null,
                    "cup_qualified": null,
                    "entry_rank": 1,
                    "entry_last_rank": 1
                },
                {
                    "id": 521322,
                    "name": "Crown Oil Ltd 2020/21",
                    "short_name": null,
                    "created": "2020-09-02T08:33:27.087313Z",
                    "closed": false,
                    "rank": null,
                    "max_entries": null,
                    "league_type": "x",
                    "scoring": "c",
                    "admin_entry": 2365250,
                    "start_event": 1,
                    "entry_can_leave": true,
                    "entry_can_admin": false,
                    "entry_can_invite": false,
                    "has_cup": false,
                    "cup_league": null,
                    "cup_qualified": null,
                    "entry_rank": 1,
                    "entry_last_rank": 1
                },
                {
                    "id": 582368,
                    "name": "Tib St NQ",
                    "short_name": null,
                    "created": "2020-09-04T08:44:21.254496Z",
                    "closed": false,
                    "rank": null,
                    "max_entries": null,
                    "league_type": "x",
                    "scoring": "c",
                    "admin_entry": 2616521,
                    "start_event": 1,
                    "entry_can_leave": true,
                    "entry_can_admin": false,
                    "entry_can_invite": false,
                    "has_cup": false,
                    "cup_league": null,
                    "cup_qualified": null,
                    "entry_rank": 1,
                    "entry_last_rank": 1
                },
                {
                    "id": 598878,
                    "name": "Supersonic Football League",
                    "short_name": null,
                    "created": "2020-09-04T17:35:28.979313Z",
                    "closed": false,
                    "rank": null,
                    "max_entries": null,
                    "league_type": "x",
                    "scoring": "c",
                    "admin_entry": 2429719,
                    "start_event": 1,
                    "entry_can_leave": true,
                    "entry_can_admin": false,
                    "entry_can_invite": false,
                    "has_cup": false,
                    "cup_league": null,
                    "cup_qualified": null,
                    "entry_rank": 1,
                    "entry_last_rank": 1
                },
                {
                    "id": 943062,
                    "name": "£100 Jackpot + £10 Mgr of Mnth",
                    "short_name": null,
                    "created": "2020-09-10T15:28:45.019870Z",
                    "closed": false,
                    "rank": null,
                    "max_entries": null,
                    "league_type": "x",
                    "scoring": "c",
                    "admin_entry": 3762509,
                    "start_event": 1,
                    "entry_can_leave": true,
                    "entry_can_admin": false,
                    "entry_can_invite": false,
                    "has_cup": false,
                    "cup_league": null,
                    "cup_qualified": null,
                    "entry_rank": 1,
                    "entry_last_rank": 1
                }
            ],
            "h2h": [],
            "cup": {
                "matches": [
                    {
                        "id": 48366805,
                        "entry_1_entry": 140082,
                        "entry_1_name": "Friend or Foden",
                        "entry_1_player_name": "Adam Bergin",
                        "entry_1_points": 37,
                        "entry_1_win": 0,
                        "entry_1_draw": 0,
                        "entry_1_loss": 0,
                        "entry_1_total": 0,
                        "entry_2_entry": 450720,
                        "entry_2_name": "Walcott Short Again",
                        "entry_2_player_name": "A Galloway",
                        "entry_2_points": 42,
                        "entry_2_win": 0,
                        "entry_2_draw": 0,
                        "entry_2_loss": 0,
                        "entry_2_total": 0,
                        "is_knockout": true,
                        "winner": 450720,
                        "seed_value": null,
                        "event": 21,
                        "tiebreak": null
                    },
                    {
                        "id": 47862478,
                        "entry_1_entry": 140082,
                        "entry_1_name": "Friend or Foden",
                        "entry_1_player_name": "Adam Bergin",
                        "entry_1_points": 95,
                        "entry_1_win": 0,
                        "entry_1_draw": 0,
                        "entry_1_loss": 0,
                        "entry_1_total": 0,
                        "entry_2_entry": 1094787,
                        "entry_2_name": "italiano",
                        "entry_2_player_name": "Italiano Alkorbi",
                        "entry_2_points": 69,
                        "entry_2_win": 0,
                        "entry_2_draw": 0,
                        "entry_2_loss": 0,
                        "entry_2_total": 0,
                        "is_knockout": true,
                        "winner": 140082,
                        "seed_value": null,
                        "event": 20,
                        "tiebreak": null
                    }
                ],
                "status": {
                    "qualification_event": 16,
                    "qualification_numbers": 4194304,
                    "qualification_rank": 55777,
                    "qualification_state": "QUALIFIED"
                },
                "cup_league": 315
            }
        },
        "name": "Friend or Foden",
        "kit": "{\"kit_shirt_type\":\"plain\",\"kit_shirt_base\":\"#4abae2\",\"kit_shirt_sleeves\":\"#ffffff\",\"kit_shirt_secondary\":\"#E1E1E1\",\"kit_shirt_logo\":\"none\",\"kit_shorts\":\"#ffffff\",\"kit_socks_type\":\"plain\",\"kit_socks_base\":\"#ffffff\",\"kit_socks_secondary\":\"#E1E1E1\"}",
        "last_deadline_bank": 7,
        "last_deadline_value": 1039,
        "last_deadline_total_transfers": 48
    }
]